README.md
setup.py
gwpwall/__init__.py
gwpwall/wall.py
gwpwall.egg-info/PKG-INFO
gwpwall.egg-info/SOURCES.txt
gwpwall.egg-info/dependency_links.txt
gwpwall.egg-info/requires.txt
gwpwall.egg-info/top_level.txt