Metadata-Version: 2.1
Name: gwpwall
Version: 1.0.0
Summary: Green-Wall-Project Wall package
Author: Gal Sajko
License: MIT
